ff_espn_api/__init__.py
ff_espn_api/box_player.py
ff_espn_api/box_score.py
ff_espn_api/constant.py
ff_espn_api/league.py
ff_espn_api/matchup.py
ff_espn_api/pick.py
ff_espn_api/player.py
ff_espn_api/settings.py
ff_espn_api/team.py
ff_espn_api/trade.py
ff_espn_api/utils.py
ff_espn_api-1.0.10.dist-info/LICENSE
ff_espn_api-1.0.10.dist-info/METADATA
ff_espn_api-1.0.10.dist-info/WHEEL
ff_espn_api-1.0.10.dist-info/top_level.txt
ff_espn_api-1.0.10.dist-info/RECORD
