Metadata-Version: 2.1
Name: ff-espn-api
Version: 1.0.10
Summary: Fantasy Football ESPN API
Home-page: https://github.com/cwendt94/ff-espn-api
Author: Christian Wendt
Author-email: UNKNOWN
License: UNKNOWN
Platform: UNKNOWN
Classifier: Programming Language :: Python :: 3
Classifier: License :: OSI Approved :: MIT License
Classifier: Operating System :: OS Independent
Requires-Dist: requests (<3.0.0,>=2.0.0)
